{
  "Fonds des Nations unies pour l'enfance": "Value 1: ORG, Value 2: ORG",
  "Performing Live": "Value 1: MISC, Value 2: MISC",
  "Afrique": "Value 1: LOC, Value 2: LOC",
  "Le Pyanet": "Value 1: LOC, Value 2: LOC",
  "Costebelle": "Value 1: LOC, Value 2: LOC",
  "Surface and Depth": "Value 1: MISC, Value 2: MISC",
  "10 Downing Street": "Value 1: MISC, Value 2: LOC",
  "Adrian": "Value 1: PER, Value 2: PER",
  "Centrale féline Belge": "Value 1: ORG, Value 2: ORG",
  "Hollywood": "Value 1: LOC, Value 2: LOC",
  "Premier ministre": "Value 1: MISC, Value 2: MISC",
  "Joscelin": "Value 1: PER, Value 2: PER",
  "El Niño": "Value 1: LOC, Value 2: LOC",
  "Narcisse Pigeon": "Value 1: PER, Value 2: PER",
  "Antilles": "Value 1: LOC, Value 2: LOC",
  "Tarascon": "Value 1: LOC, Value 2: LOC",
  "Les Borrels": "Value 1: LOC, Value 2: LOC",
  "Maroc": "Value 1: LOC, Value 2: LOC",
  "Shusterman": "Value 1: LOC, Value 2: PER",
  "Révolution française": "Value 1: MISC, Value 2: MISC",
  "Bouches-du-Rhône": "Value 1: LOC, Value 2: LOC",
  "La Capte": "Value 1: MISC, Value 2: LOC",
  "Hugues Mingarelli": "Value 1: PER, Value 2: PER",
  "département de la Frise": "Value 1: LOC, Value 2: LOC",
  "L'Almanarre": "Value 1: LOC, Value 2: LOC",
  "Paris": "Value 1: LOC, Value 2: LOC",
  "France": "Value 1: LOC, Value 2: LOC",
  "L'Ayguade": "Value 1: MISC, Value 2: LOC",
  "Dieu": "Value 1: MISC, Value 2: PER",
  "Collégiale Royale Sainte-Marthe": "Value 1: LOC, Value 2: LOC",
  "Bordeaux": "Value 1: LOC, Value 2: LOC",
  "Margaret Thatcher": "Value 1: PER, Value 2: PER",
  "Oural": "Value 1: LOC, Value 2: LOC",
  "Saintes": "Value 1: PER, Value 2: LOC",
  "UE": "Value 1: ORG, Value 2: ORG",
  "CFB": "Value 1: ORG, Value 2: ORG",
  "Giens": "Value 1: LOC, Value 2: LOC",
  "Hyères": "Value 1: LOC, Value 2: LOC",
  "Aquitaine": "Value 1: LOC, Value 2: LOC",
  "Leeuwarden": "Value 1: LOC, Value 2: LOC",
  "Practicing Philosophy": "Value 1: PER, Value 2: MISC"
}