{
  "Conseil": "ORG",
  "un livre": "AMOUNT",
  "2 semaines": "AMOUNT",
  "18 ans": "AMOUNT",
  "à partir de 1950": "TIME",
  "Le 17 mai 2004": "TIME",
  "en 1962": "TIME",
  "en 1933": "TIME",
  "en 1994": "TIME",
  "le jour": "TIME",
  "dès septembre 2004": "TIME",
  "20 janvier 1994": "TIME",
  "Aujourd'hui": "TIME",
  "pour cette nouvelle année": "TIME",
  "28 mai 2004": "TIME",
  "le 2 octobre 2006": "TIME",
  "dès le mois d'avril 1915": "TIME",
  "délégués syndicaux": "FUNC",
  "ministre socialiste du Budget": "FUNC",
  "procureur": "FUNC",
  "juges ": "FUNC",
  "auteur": "FUNC",
  "Banque d'Indochine": "ORG",
  "entreprise": "ORG",
  "Parlement": "ORG",
  "forêt": "LOC",
  "Meuse": "LOC",
  "France": "LOC",
  "Afrique": "LOC",
  "Taïwan": "LOC",
  "Chine": "LOC",
  "Créteil": "LOC",
  "ville de ": "LOC",
  "USA": "LOC",
  "UE": "LOC",
  "Europe": "LOC",
  "Francis Poullain": "PER",
  "François Mitterrand": "PER",
  "René Bousquet": "PER",
  "Michel Charasse": "PER",
  "Blanche Maupas": "PER",
  "Nicolas Sarkozy": "PER",
  "Charasse": "PER",
  "Andrew Wang": "PER",
  "Théophile Maupas": "PER",
  "Stanley Kubrick": "PER",
  "plusieurs décennies": "AMOUNT"
}
